slimcuda/__init__.py
slimcuda/cuda_gl_map.py
slimcuda/slimcuda.py
slimcuda/slimcuda_base.py
slimcuda/slimcuda_toolkit.py
slimcuda/build/slimcuda_og.ptx
slimcuda/src/slimcuda_og.cu
slimcuda/src/slimcuda_params.cu
slimcuda/src/slimcuda_params.cuh
slimcuda-0.7.5.dist-info/METADATA
slimcuda-0.7.5.dist-info/WHEEL
slimcuda-0.7.5.dist-info/top_level.txt
slimcuda-0.7.5.dist-info/RECORD
