Metadata-Version: 2.4
Name: slimcuda
Version: 0.7.5
Summary: GPU-accelerated backend for large-scale hologram generation and SLM wavefront synthesis.
Author-email: jwangXTS <junlei.wang@me.com>
License: MIT
Requires-Python: >=3.10
Requires-Dist: numpy>=2.2
Requires-Dist: cupy-cuda12x<14.0,>=13.0
Requires-Dist: PyOpengl
Requires-Dist: opencv-python
Requires-Dist: cuda-python<13.0,>=12.4
Requires-Dist: glfw
Requires-Dist: matplotlib
